scanhub/__init__.py
scanhub/_version.py
scanhub/workflows/__init__.py
scanhub/workflows/mri.py
scanhub-0.0.4.dist-info/LICENSE
scanhub-0.0.4.dist-info/METADATA
scanhub-0.0.4.dist-info/WHEEL
scanhub-0.0.4.dist-info/top_level.txt
scanhub-0.0.4.dist-info/RECORD
