Metadata-Version: 2.1
Name: scanhub
Version: 0.0.4
Summary: ScanHub Tools
Home-page: https://github.com/brain-link/scanhub_tools
Maintainer: Christoph Dinh
Maintainer-email: christoph.dinh@brain-link.de
License: BSD-licenced (3 clause)
Download-URL: https://github.com/brain-link/scanhub_tools
Project-URL: Source, https://github.com/brain-link/scanhub_tools/
Project-URL: Tracker, https://github.com/brain-link/scanhub_tools/issues/
Keywords: ScanHub MRI MEG EEG
Platform: any
Classifier: Intended Audience :: Science/Research
Classifier: Intended Audience :: Developers
Classifier: License :: OSI Approved :: BSD License
Classifier: Topic :: Scientific/Engineering
Classifier: Programming Language :: Python :: 3
Classifier: Development Status :: 1 - Planning
Classifier: Operating System :: OS Independent
Requires-Python: >=3.7
License-File: LICENSE
Requires-Dist: pydantic (==1.10.2)
